aic_tools_pinecone/__init__.py
aic_tools_pinecone-1.0.2.dist-info/METADATA
aic_tools_pinecone-1.0.2.dist-info/WHEEL
aic_tools_pinecone-1.0.2.dist-info/top_level.txt
aic_tools_pinecone-1.0.2.dist-info/RECORD
